[
  {
    "model": "apps.todo",
    "pk": 1,
    "fields": {
      "userId": 1,
      "title": "delectus aut autem",
      "completed": false
    }
  },
  {
    "model": "apps.todo",
    "pk": 2,
    "fields": {
      "userId": 1,
      "title": "quis ut nam facilis et officia qui",
      "completed": false
    }
  },
  {
    "model": "apps.todo",
    "pk": 3,
    "fields": {
      "userId": 1,
      "title": "fugiat veniam minus",
      "completed": false
    }
  },
  {
    "model": "apps.todo",
    "pk": 4,
    "fields": {
      "userId": 1,
      "title": "et porro tempora",
      "completed": true
    }
  },
  {
    "model": "apps.todo",
    "pk": 5,
    "fields": {
      "userId": 1,
      "title": "laboriosam mollitia et enim quasi adipisci quia provident illum",
      "completed": false
    }
  },
  {
    "model": "apps.todo",
    "pk": 6,
    "fields": {
      "userId": 1,
      "title": "qui ullam ratione quibusdam voluptatem quia omnis",
      "completed": false
    }
  },
  {
    "model": "apps.todo",
    "pk": 7,
    "fields": {
      "userId": 1,
      "title": "illo expedita consequatur quia in",
      "completed": false
    }
  },
  {
    "model": "apps.todo",
    "pk": 8,
    "fields": {
      "userId": 1,
      "title": "quo adipisci enim quam ut ab",
      "completed": true
    }
  },
  {
    "model": "apps.todo",
    "pk": 9,
    "fields": {
      "userId": 1,
      "title": "molestiae perspiciatis ipsa",
      "completed": false
    }
  },
  {
    "model": "apps.todo",
    "pk": 10,
    "fields": {
      "userId": 1,
      "title": "illo est ratione doloremque quia maiores aut",
      "completed": true
    }
  },
  {
    "model": "apps.todo",
    "pk": 11,
    "fields": {
      "userId": 1,
      "title": "vero rerum temporibus dolor",
      "completed": true
    }
  },
  {
    "model": "apps.todo",
    "pk": 12,
    "fields": {
      "userId": 1,
      "title": "ipsa repellendus fugit nisi",
      "completed": true
    }
  },
  {
    "model": "apps.todo",
    "pk": 13,
    "fields": {
      "userId": 1,
      "title": "et doloremque nulla",
      "completed": false
    }
  },
  {
    "model": "apps.todo",
    "pk": 14,
    "fields": {
      "userId": 1,
      "title": "repellendus sunt dolores architecto voluptatum",
      "completed": true
    }
  },
  {
    "model": "apps.todo",
    "pk": 15,
    "fields": {
      "userId": 1,
      "title": "ab voluptatum amet voluptas",
      "completed": true
    }
  },
  {
    "model": "apps.todo",
    "pk": 16,
    "fields": {
      "userId": 1,
      "title": "accusamus eos facilis sint et aut voluptatem",
      "completed": true
    }
  },
  {
    "model": "apps.todo",
    "pk": 17,
    "fields": {
      "userId": 1,
      "title": "quo laboriosam deleniti aut qui",
      "completed": true
    }
  },
  {
    "model": "apps.todo",
    "pk": 18,
    "fields": {
      "userId": 1,
      "title": "dolorum est consequatur ea mollitia in culpa",
      "completed": false
    }
  },
  {
    "model": "apps.todo",
    "pk": 19,
    "fields": {
      "userId": 1,
      "title": "molestiae ipsa aut voluptatibus pariatur dolor nihil",
      "completed": true
    }
  },
  {
    "model": "apps.todo",
    "pk": 20,
    "fields": {
      "userId": 1,
      "title": "ullam nobis libero sapiente ad optio sint",
      "completed": true
    }
  }
]